asyncpokepy/__init__.py
asyncpokepy/ahttp.py
asyncpokepy/client.py
asyncpokepy/exceptions.py
asyncpokepy/objects.py
asyncpokepy-0.1.4.dist-info/LICENSE
asyncpokepy-0.1.4.dist-info/METADATA
asyncpokepy-0.1.4.dist-info/WHEEL
asyncpokepy-0.1.4.dist-info/top_level.txt
asyncpokepy-0.1.4.dist-info/RECORD
